odoo10_addon_invader_sale_payment-10.0.2.0.0-nspkg.pth
odoo/addons/invader_sale_payment/__init__.py
odoo/addons/invader_sale_payment/__manifest__.py
odoo/addons/invader_sale_payment/models/__init__.py
odoo/addons/invader_sale_payment/models/payment_transaction.py
odoo/addons/invader_sale_payment/models/sale_order.py
odoo/addons/invader_sale_payment/views/payment_transaction.xml
odoo/addons/invader_sale_payment/views/sale_order.xml
odoo10_addon_invader_sale_payment-10.0.2.0.0.dist-info/METADATA
odoo10_addon_invader_sale_payment-10.0.2.0.0.dist-info/WHEEL
odoo10_addon_invader_sale_payment-10.0.2.0.0.dist-info/namespace_packages.txt
odoo10_addon_invader_sale_payment-10.0.2.0.0.dist-info/top_level.txt
odoo10_addon_invader_sale_payment-10.0.2.0.0.dist-info/RECORD
